keynet_inference/__init__.py
keynet_inference/config.py
keynet_inference/model_config.py
keynet_inference/plugin.py
keynet_inference/py.typed
keynet_inference/storage.py
keynet_inference/cli/__init__.py
keynet_inference/cli/main.py
keynet_inference/cli/commands/__init__.py
keynet_inference/cli/commands/push.py
keynet_inference/clients/__init__.py
keynet_inference/clients/backend.py
keynet_inference/clients/docker.py
keynet_inference/clients/models.py
keynet_inference/function/__init__.py
keynet_inference/function/builder.py
keynet_inference/function/decorator.py
keynet_inference/function/models.py
keynet_inference/function/validator.py
keynet_inference/function/venv_manager.py
keynet_inference-0.8.5.dist-info/METADATA
keynet_inference-0.8.5.dist-info/WHEEL
keynet_inference-0.8.5.dist-info/entry_points.txt
keynet_inference-0.8.5.dist-info/RECORD
