Metadata-Version: 2.4
Name: keynet-inference
Version: 0.8.5
Summary: Inference utilities for keynet - Triton Inference Server integration
Project-URL: Homepage, https://github.com/WIM-Corporation/keynet
Project-URL: Bug Tracker, https://github.com/WIM-Corporation/keynet/issues
Author-email: hbjs <hbjs97@naver.com>
License: MIT
Keywords: deployment,inference,keynet,machine-learning,triton
Classifier: Development Status :: 3 - Alpha
Classifier: Intended Audience :: Developers
Classifier: License :: OSI Approved :: MIT License
Classifier: Programming Language :: Python :: 3
Classifier: Programming Language :: Python :: 3.9
Classifier: Programming Language :: Python :: 3.10
Classifier: Programming Language :: Python :: 3.11
Classifier: Programming Language :: Python :: 3.12
Classifier: Topic :: Scientific/Engineering :: Artificial Intelligence
Requires-Python: >=3.9
Requires-Dist: cryptography>=45.0.4
Requires-Dist: docker>=7.0.0
Requires-Dist: httpx>=0.25.0
Requires-Dist: keynet-core>=0.8.0
Requires-Dist: mlflow==3.1.1
Requires-Dist: numpy<2.0,>=1.25.0
Requires-Dist: requests
Requires-Dist: rich>=13.0.0
Requires-Dist: tqdm==4.67.1
Requires-Dist: tritonclient[grpc,http]>=2.36.0
